fronts/D.py
fronts/__init__.py
fronts/_boltzmann.py
fronts/_inverse.py
fronts/_rootfinding.py
fronts/_semiinfinite.py
fronts/py.typed
fronts-1.2.7.dist-info/licenses/LICENSE.txt
fronts-1.2.7.dist-info/METADATA
fronts-1.2.7.dist-info/WHEEL
fronts-1.2.7.dist-info/top_level.txt
fronts-1.2.7.dist-info/RECORD
