Metadata-Version: 2.4
Name: fronts
Version: 1.2.7
Summary: Numerical library for nonlinear diffusion problems in semi-infinite domains
Author-email: "Gabriel S. Gerlero" <ggerlero@cimec.unl.edu.ar>
Project-URL: Homepage, https://github.com/gerlero/fronts
Project-URL: Repository, https://github.com/gerlero/fronts
Project-URL: Documentation, https://fronts.readthedocs.io
Project-URL: Changelog, https://github.com/gerlero/fronts/blob/main/CHANGELOG.md
Classifier: Development Status :: 5 - Production/Stable
Classifier: Intended Audience :: Science/Research
Classifier: License :: OSI Approved :: BSD License
Classifier: Programming Language :: Python
Classifier: Programming Language :: Python :: 3
Classifier: Programming Language :: Python :: 3.7
Classifier: Programming Language :: Python :: 3.8
Classifier: Programming Language :: Python :: 3.9
Classifier: Programming Language :: Python :: 3.10
Classifier: Programming Language :: Python :: 3.11
Classifier: Programming Language :: Python :: 3.12
Classifier: Programming Language :: Python :: 3.13
Classifier: Topic :: Scientific/Engineering :: Physics
Classifier: Topic :: Software Development :: Libraries
Classifier: Typing :: Typed
Classifier: Operating System :: OS Independent
Requires-Python: >=3.7
License-File: LICENSE.txt
Requires-Dist: scipy<2,>=1.4.0
Requires-Dist: numpy<3,>=1
Requires-Dist: sympy<2,>=1
Requires-Dist: typing-extensions<5,>=4; python_version < "3.8"
Provides-Extra: examples
Requires-Dist: matplotlib<4,>=3; extra == "examples"
Provides-Extra: lint
Requires-Dist: ruff; extra == "lint"
Provides-Extra: typing
Requires-Dist: mypy<2,>=1; extra == "typing"
Requires-Dist: scipy-stubs; python_version >= "3.10" and extra == "typing"
Provides-Extra: test
Requires-Dist: pytest<9,>=7; extra == "test"
Requires-Dist: pytest-cov; extra == "test"
Requires-Dist: fronts[examples]; extra == "test"
Provides-Extra: doc
Requires-Dist: sphinx<9,>=5; extra == "doc"
Requires-Dist: sphinx_rtd_theme; extra == "doc"
Provides-Extra: dev
Requires-Dist: fronts[examples]; extra == "dev"
Requires-Dist: fronts[lint]; extra == "dev"
Requires-Dist: fronts[typing]; extra == "dev"
Requires-Dist: fronts[test]; extra == "dev"
Requires-Dist: fronts[doc]; extra == "dev"
Dynamic: license-file
